osp/__init__.py
osp/app/__init__.py
osp/app/click.py
osp/app/dependencies.py
osp/app/main.py
osp/app/models.py
osp/app/s3.py
osp/app/tasks.py
osp/core/__init__.py
osp/settings/__init__.py
osp/utilities/__init__.py
osp/utilities/arcp.py
osp/utilities/boto3.py
osp/utilities/exceptions.py
osp/utilities/helper.py
osp/utilities/load.py
osp/utilities/minio.py
osp/wrappers/__init__.py
osp/wrappers/celery_workflow_wrapper/__init__.py
osp/wrappers/celery_workflow_wrapper/celery_workflow_engine.py
osp/wrappers/celery_workflow_wrapper/celery_workflow_wrapper.py
reaxpro_workflow_service-2.0.0.dist-info/LICENSE
reaxpro_workflow_service-2.0.0.dist-info/METADATA
reaxpro_workflow_service-2.0.0.dist-info/WHEEL
reaxpro_workflow_service-2.0.0.dist-info/top_level.txt
reaxpro_workflow_service-2.0.0.dist-info/RECORD
