Metadata-Version: 2.1
Name: reaxpro-workflow-service
Version: 2.0.0
Summary: A package running semantically enriched workflows with SimPhoNy and Celery
Author: Matthias Büschelberger, Kiran Kumaraswamy
Author-email: matthias.bueschelberger@iwm.fraunhofer.de
Classifier: Programming Language :: Python :: 3
Classifier: License :: OSI Approved :: BSD License
Classifier: Operating System :: OS Independent
Requires-Python: >=3.6
License-File: LICENSE
Requires-Dist: shieldapi >=1.0.0
Requires-Dist: celery <6,>=5.2.3
Requires-Dist: fastapi-plugins ~=0.11.0
Requires-Dist: osp-core <4,>=3.8.0
Requires-Dist: fastapi ==0.92.0
Requires-Dist: python-multipart
Requires-Dist: httpx >=0.23.3
Requires-Dist: minio >=7.1.15
Requires-Dist: uvicorn
Requires-Dist: typing-extensions
Requires-Dist: click
Requires-Dist: boto3
Requires-Dist: arcp
Provides-Extra: dev
Requires-Dist: bumpver ==2021.1114 ; extra == 'dev'
Requires-Dist: dunamai ==1.7.0 ; extra == 'dev'
Provides-Extra: pre_commit
Requires-Dist: pre-commit ==2.15.0 ; extra == 'pre_commit'
Requires-Dist: pylint ; extra == 'pre_commit'
Provides-Extra: tests
Requires-Dist: pytest ==6.2.5 ; extra == 'tests'
Requires-Dist: pytest-celery ; extra == 'tests'
Requires-Dist: pytest-mock ; extra == 'tests'
Provides-Extra: wrappers
Requires-Dist: simphony-catalytic >=1.2.0 ; extra == 'wrappers'
